spetlrbootstrap/__init__.py
spetlrbootstrap/arguments.py
spetlrbootstrap/bootstrap.py
spetlrbootstrap/download.py
spetlrbootstrap/introspect_entrypoint.py
spetlrbootstrap/libraries.py
spetlrbootstrap-0.0.5.dist-info/LICENSE
spetlrbootstrap-0.0.5.dist-info/METADATA
spetlrbootstrap-0.0.5.dist-info/WHEEL
spetlrbootstrap-0.0.5.dist-info/entry_points.txt
spetlrbootstrap-0.0.5.dist-info/top_level.txt
spetlrbootstrap-0.0.5.dist-info/RECORD
